shell_gtranslate-0.1.dist-info/DESCRIPTION.rst
shell_gtranslate-0.1.dist-info/METADATA
shell_gtranslate-0.1.dist-info/RECORD
shell_gtranslate-0.1.dist-info/WHEEL
shell_gtranslate-0.1.dist-info/entry_points.txt
shell_gtranslate-0.1.dist-info/metadata.json
shell_gtranslate-0.1.dist-info/top_level.txt
src/__init__.py
src/api_connections.py
src/interactions.py
src/main.py
