Metadata-Version: 2.0
Name: shell-gtranslate
Version: 0.1
Summary: This is a simple translator to use in shell
Home-page: https://github.com/rodrigocam/shell-gtranslate
Author: UNKNOWN
Author-email: UNKNOWN
License: UNKNOWN
Platform: UNKNOWN
Requires-Dist: googletrans
